agileetc/__init__.py
agileetc/cli.py
agileetc/sample.py
agileetc/terminal.py
agileetc-0.0.12.dist-info/entry_points.txt
agileetc-0.0.12.dist-info/LICENSE
agileetc-0.0.12.dist-info/WHEEL
agileetc-0.0.12.dist-info/METADATA
agileetc-0.0.12.dist-info/RECORD
