Metadata-Version: 2.1
Name: agileetc
Version: 0.0.12
Summary: Future Agile CICD tooling template
Home-page: https://github.com/Agile-Solutions-GB-Ltd/automatic-eureka/tree/main/python/agileetc
License: Apache-2.0
Author: agileturret
Author-email: Paul.Gilligan@agilesolutions.co.uk
Requires-Python: >=3.9,<4.0
Classifier: License :: OSI Approved :: Apache Software License
Classifier: Programming Language :: Python :: 3
Classifier: Programming Language :: Python :: 3.9
Classifier: Programming Language :: Python :: 3.10
Requires-Dist: Fabric3 (>=1.14.post1,<2.0)
Requires-Dist: PyYAML (>=5.4.1,<6.0.0)
Requires-Dist: click (>=8.1,<9.0)
Requires-Dist: prettytable (>=3.3.0,<4.0.0)
Requires-Dist: pytest (>=7.1.3,<8.0.0)
Project-URL: Repository, https://github.com/Agile-Solutions-GB-Ltd/automatic-eureka
